RiskSimp/__init__.py
RiskSimp/Objects/__init__.py
RiskSimp/Objects/distributions.py
RiskSimp/Utils/__init__.py
RiskSimp/Utils/simulations.py
RiskSimp/Variables/__init__.py
RiskSimp/Variables/constant.py
RiskSimp/Variables/continuous.py
RiskSimp/Variables/discrete.py
RiskSimp-0.1.5.dist-info/LICENSE
RiskSimp-0.1.5.dist-info/METADATA
RiskSimp-0.1.5.dist-info/WHEEL
RiskSimp-0.1.5.dist-info/top_level.txt
RiskSimp-0.1.5.dist-info/RECORD
