Metadata-Version: 2.1
Name: RiskSimp
Version: 0.1.5
Summary: RiskSimp is a versatile Python library designed to streamline the management and manipulation of random variables to empower analysts to effortlessly integrate random distributions into their processes, facilitating non-deterministic analysis 
Home-page: https://github.com/FabioSol/RiskSimp.git
Author: Fabio Sol
Author-email: fabioso2231@gmail.com
License: MIT
License-File: LICENSE
Requires-Dist: matplotlib (~=3.7.2)
Requires-Dist: pandas (~=2.0.3)
Requires-Dist: setuptools (==68.1.2)
Requires-Dist: twine (>=3.4.1)
